rapidyaml-0.10.0.dist-info/RECORD
rapidyaml-0.10.0.dist-info/WHEEL
rapidyaml-0.10.0.dist-info/top_level.txt
rapidyaml-0.10.0.dist-info/METADATA
rapidyaml-0.10.0.dist-info/licenses/LICENSE.txt
ryml/ryml.py
ryml/version.py
ryml/_ryml.so
ryml/__init__.py
ryml/.dylibs/Python
