Metadata-Version: 2.4
Name: rapidyaml
Version: 0.10.0
Summary: Rapid YAML - a library to parse and emit YAML, and do it fast
Home-page: https://github.com/biojppm/rapidyaml
Author: Joao Paulo Magalhaes
Author-email: dev@jpmag.me
License: MIT
Requires-Python: >=3.6
License-File: LICENSE.txt
Requires-Dist: deprecation
Dynamic: author
Dynamic: author-email
Dynamic: description
Dynamic: description-content-type
Dynamic: home-page
Dynamic: license
Dynamic: license-file
Dynamic: requires-dist
Dynamic: requires-python
Dynamic: summary
